airstack/__init__.py
airstack/constant.py
airstack/execute_query.py
airstack/generic.py
airstack/popular_queries.py
airstack/send_request.py
himanshu_test-50.0.0.dist-info/METADATA
himanshu_test-50.0.0.dist-info/WHEEL
himanshu_test-50.0.0.dist-info/top_level.txt
himanshu_test-50.0.0.dist-info/RECORD
